[
    {
        "key": "dbln",
        "value": "%7B%2261568682832467%22%3A%22QbYJ1UFC%22%2C%2261568176525414%22%3A%22g3w3NTzJ%22%7D",
        "domain": "facebook.com",
        "path": "/login/device-based/",
        "hostOnly": false,
        "creation": "2025-11-29T10:42:21.859Z",
        "lastAccessed": "2025-11-29T10:42:21.859Z"
    },
    {
        "key": "sb",
        "value": "lxQiaRyqxJTVhZZAnrupVHW2",
        "domain": "facebook.com",
        "path": "/",
        "hostOnly": false,
        "creation": "2025-11-29T10:42:21.859Z",
        "lastAccessed": "2025-11-29T10:42:21.859Z"
    },
    {
        "key": "vpd",
        "value": "v1%3B665x360x1.9509830474853516",
        "domain": "facebook.com",
        "path": "/",
        "hostOnly": false,
        "creation": "2025-11-29T10:42:21.859Z",
        "lastAccessed": "2025-11-29T10:42:21.859Z"
    },
    {
        "key": "ps_l",
        "value": "1",
        "domain": "facebook.com",
        "path": "/",
        "hostOnly": false,
        "creation": "2025-11-29T10:42:21.859Z",
        "lastAccessed": "2025-11-29T10:42:21.859Z"
    },
    {
        "key": "ps_n",
        "value": "1",
        "domain": "facebook.com",
        "path": "/",
        "hostOnly": false,
        "creation": "2025-11-29T10:42:21.859Z",
        "lastAccessed": "2025-11-29T10:42:21.859Z"
    },
    {
        "key": "datr",
        "value": "nvQnaaJzzW80ItsTe4BEuotn",
        "domain": "facebook.com",
        "path": "/",
        "hostOnly": false,
        "creation": "2025-11-29T10:42:21.859Z",
        "lastAccessed": "2025-11-29T10:42:21.859Z"
    },
    {
        "key": "m_pixel_ratio",
        "value": "1.9509830474853516",
        "domain": "facebook.com",
        "path": "/",
        "hostOnly": false,
        "creation": "2025-11-29T10:42:21.859Z",
        "lastAccessed": "2025-11-29T10:42:21.859Z"
    },
    {
        "key": "pas",
        "value": "61568221289003%3AT8gXrDn4dM%2C61568682832467%3AZaJHxQGnPo%2C61568176525414%3ARL4H18VG45%2C100081901104081%3A4bZOAMfR7u",
        "domain": "facebook.com",
        "path": "/",
        "hostOnly": false,
        "creation": "2025-11-29T10:42:21.859Z",
        "lastAccessed": "2025-11-29T10:42:21.859Z"
    },
    {
        "key": "dpr",
        "value": "2.1450023651123047",
        "domain": "facebook.com",
        "path": "/",
        "hostOnly": false,
        "creation": "2025-11-29T10:42:21.859Z",
        "lastAccessed": "2025-11-29T10:42:21.859Z"
    },
    {
        "key": "locale",
        "value": "en_GB",
        "domain": "facebook.com",
        "path": "/",
        "hostOnly": false,
        "creation": "2025-11-29T10:42:21.859Z",
        "lastAccessed": "2025-11-29T10:42:21.859Z"
    },
    {
        "key": "wd",
        "value": "360x800",
        "domain": "facebook.com",
        "path": "/",
        "hostOnly": false,
        "creation": "2025-11-29T10:42:21.859Z",
        "lastAccessed": "2025-11-29T10:42:21.859Z"
    },
    {
        "key": "c_user",
        "value": "61568176525414",
        "domain": "facebook.com",
        "path": "/",
        "hostOnly": false,
        "creation": "2025-11-29T10:42:21.859Z",
        "lastAccessed": "2025-11-29T10:42:21.859Z"
    },
    {
        "key": "xs",
        "value": "12%3ABJI0E1oP9gS-Hw%3A2%3A1764412922%3A-1%3A-1",
        "domain": "facebook.com",
        "path": "/",
        "hostOnly": false,
        "creation": "2025-11-29T10:42:21.859Z",
        "lastAccessed": "2025-11-29T10:42:21.859Z"
    },
    {
        "key": "fr",
        "value": "1rYGV90nn3PtBvHQu.AWexrU7y5UuC8x0KDogbGV1a0ETC4UmjLIFgN_AAUoHWlNdYQ88.BpKsYH..AAA.0.0.BpKs38.AWddRB0zJ4w8qkFE08W-GQ5Mvro",
        "domain": "facebook.com",
        "path": "/",
        "hostOnly": false,
        "creation": "2025-11-29T10:42:21.859Z",
        "lastAccessed": "2025-11-29T10:42:21.859Z"
    },
    {
        "key": "wl_cbv",
        "value": "v2%3Bclient_version%3A3000%3Btimestamp%3A1764412924",
        "domain": "facebook.com",
        "path": "/",
        "hostOnly": false,
        "creation": "2025-11-29T10:42:21.859Z",
        "lastAccessed": "2025-11-29T10:42:21.859Z"
    },
    {
        "key": "fbl_st",
        "value": "101322441%3BT%3A29406882",
        "domain": "facebook.com",
        "path": "/",
        "hostOnly": false,
        "creation": "2025-11-29T10:42:21.859Z",
        "lastAccessed": "2025-11-29T10:42:21.859Z"
    }
]
