[
    {
        "key": "dbln",
        "value": "%7B%2261558741327527%22%3A%22tQ7MsPVG%22%7D",
        "domain": "facebook.com",
        "path": "/login/device-based/",
        "hostOnly": false,
        "creation": "2026-01-25T18:17:27.161Z",
        "lastAccessed": "2026-01-25T18:17:27.161Z"
    },
    {
        "key": "sb",
        "value": "MuZ1aZSsd_LEiSWsp0aeDRj4",
        "domain": "facebook.com",
        "path": "/",
        "hostOnly": false,
        "creation": "2026-01-25T18:17:27.161Z",
        "lastAccessed": "2026-01-25T18:17:27.161Z"
    },
    {
        "key": "ps_l",
        "value": "1",
        "domain": "facebook.com",
        "path": "/",
        "hostOnly": false,
        "creation": "2026-01-25T18:17:27.161Z",
        "lastAccessed": "2026-01-25T18:17:27.161Z"
    },
    {
        "key": "ps_n",
        "value": "1",
        "domain": "facebook.com",
        "path": "/",
        "hostOnly": false,
        "creation": "2026-01-25T18:17:27.161Z",
        "lastAccessed": "2026-01-25T18:17:27.161Z"
    },
    {
        "key": "locale",
        "value": "en_GB",
        "domain": "facebook.com",
        "path": "/",
        "hostOnly": false,
        "creation": "2026-01-25T18:17:27.161Z",
        "lastAccessed": "2026-01-25T18:17:27.161Z"
    },
    {
        "key": "vpd",
        "value": "v1%3B665x360x1.9509830474853516",
        "domain": "facebook.com",
        "path": "/",
        "hostOnly": false,
        "creation": "2026-01-25T18:17:27.161Z",
        "lastAccessed": "2026-01-25T18:17:27.161Z"
    },
    {
        "key": "dpr",
        "value": "2.1450023651123047",
        "domain": "facebook.com",
        "path": "/",
        "hostOnly": false,
        "creation": "2026-01-25T18:17:27.161Z",
        "lastAccessed": "2026-01-25T18:17:27.161Z"
    },
    {
        "key": "pas",
        "value": "61586986476180%3ANbTzY0CPTR%2C61558741327527%3AwHh7w6dQYz",
        "domain": "facebook.com",
        "path": "/",
        "hostOnly": false,
        "creation": "2026-01-25T18:17:27.161Z",
        "lastAccessed": "2026-01-25T18:17:27.161Z"
    },
    {
        "key": "m_pixel_ratio",
        "value": "1.9509830474853516",
        "domain": "facebook.com",
        "path": "/",
        "hostOnly": false,
        "creation": "2026-01-25T18:17:27.161Z",
        "lastAccessed": "2026-01-25T18:17:27.161Z"
    },
    {
        "key": "wd",
        "value": "360x800",
        "domain": "facebook.com",
        "path": "/",
        "hostOnly": false,
        "creation": "2026-01-25T18:17:27.161Z",
        "lastAccessed": "2026-01-25T18:17:27.161Z"
    },
    {
        "key": "c_user",
        "value": "61558741327527",
        "domain": "facebook.com",
        "path": "/",
        "hostOnly": false,
        "creation": "2026-01-25T18:17:27.162Z",
        "lastAccessed": "2026-01-25T18:17:27.162Z"
    },
    {
        "key": "datr",
        "value": "ql12aSkScB2oz9iHjgP2DJQf",
        "domain": "facebook.com",
        "path": "/",
        "hostOnly": false,
        "creation": "2026-01-25T18:17:27.162Z",
        "lastAccessed": "2026-01-25T18:17:27.162Z"
    },
    {
        "key": "xs",
        "value": "8%3Ajn05IksVpMCmHQ%3A2%3A1769364906%3A-1%3A-1",
        "domain": "facebook.com",
        "path": "/",
        "hostOnly": false,
        "creation": "2026-01-25T18:17:27.162Z",
        "lastAccessed": "2026-01-25T18:17:27.162Z"
    },
    {
        "key": "fr",
        "value": "0tLgLo2804LMzIQR3.AWelpiAiiJanEqac_0Y4lS4N6wclIGGCo2I15wbDZcxdxqDpUWA.BpdeYy..AAA.0.0.Bpdl2w.AWc_LFr1AvsuVabR6rbg6xA1Ifk",
        "domain": "facebook.com",
        "path": "/",
        "hostOnly": false,
        "creation": "2026-01-25T18:17:27.162Z",
        "lastAccessed": "2026-01-25T18:17:27.162Z"
    },
    {
        "key": "fbl_st",
        "value": "101219150%3BT%3A29489415",
        "domain": "facebook.com",
        "path": "/",
        "hostOnly": false,
        "creation": "2026-01-25T18:17:27.162Z",
        "lastAccessed": "2026-01-25T18:17:27.162Z"
    },
    {
        "key": "wl_cbv",
        "value": "v2%3Bclient_version%3A3064%3Btimestamp%3A1769364913",
        "domain": "facebook.com",
        "path": "/",
        "hostOnly": false,
        "creation": "2026-01-25T18:17:27.162Z",
        "lastAccessed": "2026-01-25T18:17:27.162Z"
    }
]
